rs232_to_pdu/__init__.py
rs232_to_pdu/__main__.py
rs232_to_pdu/device.py
rs232_to_pdu/eventloop.py
rs232_to_pdu/healthcheck.py
rs232_to_pdu/powerchange.py
rs232_to_pdu/serialconn.py
rs232_to_pdu/taskqueue.py
rs232_to_pdu/devices/tripplite/PDUMH20ATNET.yaml
rs232_to_pdu/devices/tripplite/PDUMH20HVATNET.yaml
rs232_to_pdu/devices/tripplite/PDUMNH20AT1.yaml
rs232_to_pdu/devices/tripplite/PDUMV30HVNETLX.yaml
rs232_to_pdu/devices/tripplite/SMART3000RM2UL.yaml
rs232_to_pdu/parsers/__init__.py
rs232_to_pdu/parsers/base.py
rs232_to_pdu/parsers/kvmseq.py
rs232_to_pdu/transport/__init__.py
rs232_to_pdu/transport/base.py
rs232_to_pdu/transport/snmp.py
rs232_to_pdu-1.1.9.dist-info/LICENSE
rs232_to_pdu-1.1.9.dist-info/METADATA
rs232_to_pdu-1.1.9.dist-info/WHEEL
rs232_to_pdu-1.1.9.dist-info/top_level.txt
rs232_to_pdu-1.1.9.dist-info/RECORD
