Metadata-Version: 2.1
Name: rs232-to-pdu
Version: 1.1.9
Summary: Converts RS232 serial data to SNMP commands to control PDUs.
Author: InkBridge Networks
License-File: LICENSE
Requires-Dist: APScheduler==3.10.4
Requires-Dist: astroid
Requires-Dist: certifi
Requires-Dist: cffi
Requires-Dist: charset-normalizer
Requires-Dist: cryptography
Requires-Dist: dill
Requires-Dist: idna
Requires-Dist: isort
Requires-Dist: Jinja2
Requires-Dist: MarkupSafe
Requires-Dist: mccabe
Requires-Dist: platformdirs
Requires-Dist: ply
Requires-Dist: pyasn1==0.6.0
Requires-Dist: pycparser
Requires-Dist: pyserial==3.5
Requires-Dist: pysmi
Requires-Dist: pysnmp==6.2.5
Requires-Dist: pysnmpcrypto
Requires-Dist: pytz
Requires-Dist: requests
Requires-Dist: six
Requires-Dist: snmpsim
Requires-Dist: systemd-watchdog==0.9.0
Requires-Dist: tomlkit
Requires-Dist: tzlocal
Requires-Dist: urllib3
Requires-Dist: watchdog==5.0.0
Requires-Dist: pyyaml
